binary_inspector/__init__.py
binary_inspector/binary.py
binary_inspector/blint_binary.py
binary_inspector/blint_binary.py.ABOUT
binary_inspector/blint_binary.py.LICENSE
binary_inspector/config.py
binary_inspector/plugin.py
binary_inspector-0.2.0.dist-info/licenses/AUTHORS.rst
binary_inspector-0.2.0.dist-info/licenses/CHANGELOG.rst
binary_inspector-0.2.0.dist-info/licenses/CODE_OF_CONDUCT.rst
binary_inspector-0.2.0.dist-info/licenses/NOTICE
binary_inspector-0.2.0.dist-info/licenses/README.rst
binary_inspector-0.2.0.dist-info/licenses/apache-2.0.LICENSE
binary_inspector-0.2.0.dist-info/METADATA
binary_inspector-0.2.0.dist-info/WHEEL
binary_inspector-0.2.0.dist-info/entry_points.txt
binary_inspector-0.2.0.dist-info/top_level.txt
binary_inspector-0.2.0.dist-info/RECORD
